StenoCLI/Image.py
StenoCLI/Text.py
StenoCLI/__init__.py
StenoCLI/__main__.py
stenocli-0.0.3.dist-info/LICENSE
stenocli-0.0.3.dist-info/METADATA
stenocli-0.0.3.dist-info/WHEEL
stenocli-0.0.3.dist-info/dependency_links.txt
stenocli-0.0.3.dist-info/entry_points.txt
stenocli-0.0.3.dist-info/top_level.txt
stenocli-0.0.3.dist-info/RECORD
